{"id":"PD2+","dependencies":[{"name":"/Users/nick/projects/tomespark/node_modules/lodash/package.json","includedInParent":true,"mtime":499162500000},{"name":"/Users/nick/projects/tomespark/package.json","includedInParent":true,"mtime":1534115700413},{"name":"/Users/nick/projects/tomespark/.babelrc","includedInParent":true,"mtime":1533367520439}],"generated":{"js":"var e={};module.exports=e;","map":{"mappings":[{"source":"../node_modules/lodash/_realNames.js","original":{"line":2,"column":0},"generated":{"line":1,"column":0}},{"source":"../node_modules/lodash/_realNames.js","original":{"line":2,"column":0},"generated":{"line":1,"column":4}},{"source":"../node_modules/lodash/_realNames.js","original":{"line":2,"column":0},"generated":{"line":1,"column":6}},{"source":"../node_modules/lodash/_realNames.js","original":{"line":4,"column":0},"generated":{"line":1,"column":9}},{"source":"../node_modules/lodash/_realNames.js","original":{"line":4,"column":0},"generated":{"line":1,"column":16}},{"source":"../node_modules/lodash/_realNames.js","original":{"line":4,"column":0},"generated":{"line":1,"column":24}}],"sources":{"../node_modules/lodash/_realNames.js":"/** Used to lookup unminified function names. */\nvar realNames = {};\n\nmodule.exports = realNames;\n"},"lineCount":null}},"hash":"4cbfd17cd82ede7dc6a3303c15b33ff3","cacheData":{"env":{}}}